objectory/__init__.py
objectory/abstract_factory.py
objectory/constants.py
objectory/errors.py
objectory/py.typed
objectory/registry.py
objectory/universal.py
objectory/utils/__init__.py
objectory/utils/config.py
objectory/utils/instantiation.py
objectory/utils/introspection.py
objectory/utils/name_resolution.py
objectory/utils/object_helpers.py
objectory-0.3.1.dist-info/METADATA
objectory-0.3.1.dist-info/WHEEL
objectory-0.3.1.dist-info/licenses/LICENSE
objectory-0.3.1.dist-info/RECORD
