Metadata-Version: 2.4
Name: objectory
Version: 0.3.1
Dynamic: Maintainer
Dynamic: Maintainer-email
Summary: A light library for general purpose object factories
Project-URL: homepage, https://github.com/durandtibo/objectory
Project-URL: repository, https://github.com/durandtibo/objectory
Project-URL: documentation, https://durandtibo.github.io/objectory/
Author-email: Thibaut Durand <durand.tibo+gh@gmail.com>
License-Expression: BSD-3-Clause
License-File: LICENSE
Keywords: abstract factory,factory,registry
Classifier: Development Status :: 4 - Beta
Classifier: Intended Audience :: Developers
Classifier: Intended Audience :: Information Technology
Classifier: Intended Audience :: Science/Research
Classifier: License :: OSI Approved :: BSD License
Classifier: Operating System :: POSIX :: Linux
Classifier: Programming Language :: Python :: 3.10
Classifier: Programming Language :: Python :: 3.11
Classifier: Programming Language :: Python :: 3.12
Classifier: Programming Language :: Python :: 3.13
Classifier: Programming Language :: Python :: 3.14
Classifier: Topic :: Scientific/Engineering
Classifier: Topic :: Software Development :: Libraries
Requires-Python: >=3.10
